notears_pytorch.py
notears_pytorch-0.3.0.dist-info/METADATA
notears_pytorch-0.3.0.dist-info/WHEEL
notears_pytorch-0.3.0.dist-info/top_level.txt
notears_pytorch-0.3.0.dist-info/RECORD
