Metadata-Version: 2.4
Name: notears-pytorch
Version: 0.3.0
Summary: A PyTorch implementation of the NOTEARS Linear algorithm for causal discovery.
Home-page: https://github.com/rajoy99/notears-pytorch
Author: Rafat Ashraf Joy
Author-email: rafat.joy99@gmail.com
Keywords: causal-discovery,structure-learning,dag,pytorch,notears,notears-linear,linear causal discovery,causal discovery gpu
Classifier: Programming Language :: Python :: 3
Classifier: License :: OSI Approved :: MIT License
Classifier: Operating System :: OS Independent
Classifier: Topic :: Scientific/Engineering :: Artificial Intelligence
Requires-Python: >=3.6
Requires-Dist: numpy
Requires-Dist: torch>=1.0.0
Dynamic: author
Dynamic: author-email
Dynamic: classifier
Dynamic: description
Dynamic: description-content-type
Dynamic: home-page
Dynamic: keywords
Dynamic: requires-dist
Dynamic: requires-python
Dynamic: summary
